astel/__init__.py
astel/agent.py
astel/cli.py
astel/crawler.py
astel/errors.py
astel/events.py
astel/filters.py
astel/limiters.py
astel/options.py
astel/parsers.py
astel-0.1.1.dist-info/LICENSE
astel-0.1.1.dist-info/METADATA
astel-0.1.1.dist-info/WHEEL
astel-0.1.1.dist-info/entry_points.txt
astel-0.1.1.dist-info/RECORD
